README.md
setup.py
django_weebly.egg-info/PKG-INFO
django_weebly.egg-info/SOURCES.txt
django_weebly.egg-info/dependency_links.txt
django_weebly.egg-info/not-zip-safe
django_weebly.egg-info/top_level.txt
marto_python/__init__.py
marto_python/admin.py
marto_python/cache.py
marto_python/collections.py
marto_python/context_processors.py
marto_python/continents.py
marto_python/cookies.py
marto_python/exceptions.py
marto_python/files.py
marto_python/pagination.py
marto_python/scrapy.py
marto_python/strings.py
marto_python/threads.py
marto_python/url.py
marto_python/util.py
marto_python/webfaction_fab.py
marto_python/email/__init__.py
marto_python/email/admin.py
marto_python/email/backend.py
marto_python/email/email.py
marto_python/email/models.py
marto_python/email/jobs/__init__.py
marto_python/email/jobs/send_emails.py
marto_python/email/management/__init__.py
marto_python/email/management/commands/__init__.py
marto_python/email/management/commands/clean_error_emails.py
marto_python/email/migrations/0001_initial.py
marto_python/email/migrations/0002_auto_20160815_1134.py
marto_python/email/migrations/0003_auto_20160820_1238.py
marto_python/email/migrations/0004_auto_20190213_1849.py
marto_python/email/migrations/0005_auto_20190215_0041.py
marto_python/email/migrations/__init__.py
marto_python/management/__init__.py
marto_python/management/commands/__init__.py
marto_python/management/commands/runserver_quiet.py
marto_python/pages/__init__.py
marto_python/pages/admin.py
marto_python/pages/context_processors.py
marto_python/pages/models.py
marto_python/pages/views.py
marto_python/pages/migrations/0001_initial.py
marto_python/pages/migrations/__init__.py
weebly/__init__.py
weebly/admin.py
weebly/apps.py
weebly/models.py
weebly/signals.py
weebly/tests.py
weebly/util.py
weebly/views.py
weebly/management/__init__.py
weebly/management/commands/__init__.py
weebly/management/commands/notify_payments.py
weebly/migrations/0001_initial.py
weebly/migrations/__init__.py